{
  "$schema": "https://ui.shadcn.com/schema/registry-item.json",
  "name": "solid/utils",
  "type": "registry:component",
  "title": "Utilities (Solid)",
  "description": "Utilities for SolidJS.",
  "dependencies": [
    "clsx",
    "tailwind-merge"
  ],
  "files": [
    {
      "path": "registry/solid/lib/utils.ts",
      "content": "import { clsx, type ClassValue } from \"clsx\"\nimport { twMerge } from \"tailwind-merge\"\n\nexport function cn(...inputs: ClassValue[]) {\n  return twMerge(clsx(inputs))\n}\n\nexport const omniMonoText = {\n  compact: \"font-mono text-[10px] uppercase tracking-[0.24em]\",\n  base: \"font-mono text-[10px] uppercase tracking-[0.28em]\",\n  wide: \"font-mono text-[10px] uppercase tracking-[0.32em]\",\n  section: \"font-mono text-xs uppercase tracking-[0.32em]\",\n  menu: \"font-mono text-[11px] uppercase tracking-[0.28em]\",\n} as const\n",
      "type": "registry:lib"
    }
  ]
}